mkasynx/__init__.py
mkasynx/entry.py
mkdocs_asynx-0.0.0.dist-info/LICENSE
mkdocs_asynx-0.0.0.dist-info/METADATA
mkdocs_asynx-0.0.0.dist-info/WHEEL
mkdocs_asynx-0.0.0.dist-info/entry_points.txt
mkdocs_asynx-0.0.0.dist-info/top_level.txt
mkdocs_asynx-0.0.0.dist-info/RECORD
