Metadata-Version: 2.1
Name: mkdocs-asynx
Version: 0.0.0
Summary: A pluging makes asynx.dev Team to build https://asynx.dev
Home-page: https://github.com/asynx-dev/mkdocs-asynx-plugin
Author: Alper Yazar
License: UNKNOWN
Platform: UNKNOWN
Classifier: License :: OSI Approved :: The Unlicense (Unlicense)
Classifier: Topic :: Documentation
Classifier: Topic :: Text Processing
Classifier: Development Status :: 2 - Pre-Alpha
Classifier: Intended Audience :: Developers
Classifier: Operating System :: OS Independent
Classifier: Programming Language :: Python :: 3
Requires-Python: >=3.6
Requires-Dist: mkdocs (>=1.1)
